volttron/driver/interfaces/bacnet/__init__.py
volttron/driver/interfaces/bacnet/bacnet.py
volttron_lib_bacnet_driver-2.0.0rc2.dist-info/METADATA
volttron_lib_bacnet_driver-2.0.0rc2.dist-info/WHEEL
volttron_lib_bacnet_driver-2.0.0rc2.dist-info/RECORD
