Metadata-Version: 2.3
Name: volttron-lib-bacnet-driver
Version: 2.0.0rc2
Summary: BACnet driver supported and maintained by the Volttron team.
License: Apache-2.0
Author: Mark Bonicillo
Author-email: volttron@pnnl.gov
Requires-Python: >=3.10,<4.0
Classifier: Intended Audience :: Developers
Classifier: Intended Audience :: Information Technology
Classifier: Intended Audience :: Other Audience
Classifier: Intended Audience :: Science/Research
Classifier: License :: OSI Approved :: Apache Software License
Classifier: Programming Language :: Python :: 3
Classifier: Programming Language :: Python :: 3.10
Classifier: Programming Language :: Python :: 3.11
Classifier: Programming Language :: Python :: 3.12
Classifier: Programming Language :: Python :: 3.13
Classifier: Programming Language :: Python :: 3 :: Only
Requires-Dist: bacpypes3 (>=0.0.102)
Requires-Dist: protocol-proxy-bacnet (>=2.0.0rc0)
Requires-Dist: volttron-lib-base-driver (>=2.0.0rc0)
Project-URL: Homepage, https://github.com/eclipse-volttron/volttron-lib-bacnet-driver
Project-URL: Repository, https://github.com/eclipse-volttron/volttron-lib-bacnet-driver
